kssbox/__init__.py
kssbox/main.py
kssbox-1.0.4.dist-info/LICENSE
kssbox-1.0.4.dist-info/METADATA
kssbox-1.0.4.dist-info/WHEEL
kssbox-1.0.4.dist-info/top_level.txt
kssbox-1.0.4.dist-info/RECORD
