Metadata-Version: 2.1
Name: kssbox
Version: 1.0.4
Summary: harness python sdk package
Author-email: kevin brother <1301239018@qq.com>
License: Copyright (c) 2018 The Python Packaging Authority
Keywords: kssbox,add,test
Classifier: Programming Language :: Python :: 3
Classifier: License :: OSI Approved :: MIT License
Classifier: Operating System :: OS Independent
Requires-Python: >=3.6
License-File: LICENSE
